INSTALL.rst
MANIFEST.in
README.rst
VERSION
setup.cfg
setup.py
src/pytunol/__init__.py
src/pytunol/__main__.py
src/pytunol/__meta__.py
src/pytunol/console.py
src/pytunol/keywords.py
src/pytunol/transpyler.py
src/pytunol.egg-info/PKG-INFO
src/pytunol.egg-info/SOURCES.txt
src/pytunol.egg-info/dependency_links.txt
src/pytunol.egg-info/entry_points.txt
src/pytunol.egg-info/not-zip-safe
src/pytunol.egg-info/requires.txt
src/pytunol.egg-info/top_level.txt
src/pytunol/tests/__init__.py