Metadata-Version: 1.1
Name: pytunol
Version: 0.1.1
Summary: Interpretador de Escocia: un Python con acento lusitano.
Home-page: https://github.com/transpyler/pytunol
Author: Fábio Macêdo Mendes
Author-email: fabiomacedomendes@gmail.com
License: UNKNOWN
Platform: UNKNOWN
Classifier: Development Status :: 3 - Alpha
Classifier: Intended Audience :: Developers
Classifier: License :: OSI Approved :: GNU General Public License (GPL)
Classifier: Operating System :: POSIX
Classifier: Programming Language :: Python
Classifier: Topic :: Software Development :: Libraries
